{
  "tx_id": "d17e15d2-bfbe-44ce-a1c7-123684caa79d",
  "account_id": "acc_151",
  "amount": 26.02,
  "timestamp": "2025-11-26T01:40:44.229962+00:00",
  "reason": [
    "velocity_5m",
    "suspicious_country"
  ],
  "ml_score": 0.23380623977981035,
  "rules": [
    {
      "id": "velocity_5m",
      "severity": "medium",
      "description": "Plus de 5 transactions en 5 minutes"
    },
    {
      "id": "suspicious_country",
      "severity": "high",
      "description": "Transaction depuis pays \u00c3\u00a0 risque"
    }
  ]
}