{
  "tx_id": "8cb07e6d-694d-4779-8846-5548d6ed2e5c",
  "account_id": "acc_653",
  "amount": 7.89,
  "timestamp": "2025-11-26T04:40:52.229962+00:00",
  "reason": [
    "velocity_5m",
    "suspicious_country"
  ],
  "ml_score": 0.19104420707768632,
  "rules": [
    {
      "id": "velocity_5m",
      "severity": "medium",
      "description": "Plus de 5 transactions en 5 minutes"
    },
    {
      "id": "suspicious_country",
      "severity": "high",
      "description": "Transaction depuis pays \u00c3\u00a0 risque"
    }
  ]
}